RiboMiner/CoverageOfEachTrans.py
RiboMiner/EnrichmentAnalysis.py
RiboMiner/EnrichmentAnalysisForSingleTrans.py
RiboMiner/ExtractSequenceCenteredOnAPosition.py
RiboMiner/FunctionDefinition.py
RiboMiner/GCContent.py
RiboMiner/GetProteinCodingSequence.py
RiboMiner/GetUTRSequences.py
RiboMiner/LengthDistribution.py
RiboMiner/MergeSampleDensitys.py
RiboMiner/MetageneAnalysis.py
RiboMiner/MetageneAnalysisForTheWholeRegions.py
RiboMiner/ModifyHTseq.py
RiboMiner/OutputTranscriptInfo.py
RiboMiner/PausingScore.py
RiboMiner/Periodicity.py
RiboMiner/PlotEnrichmentRatio.py
RiboMiner/PlotGCContent.py
RiboMiner/PlotHydropathyCharge.py
RiboMiner/PlotMetageneAnalysis.py
RiboMiner/PlotMetageneAnalysisForTheWholeRegions.py
RiboMiner/PlotPolarity.py
RiboMiner/PlotRiboDensityAroundTriAAMotifs.py
RiboMiner/PlotRiboDensityAtEachKindAAOrCodon.py
RiboMiner/PlotTransCoverage.py
RiboMiner/PolarityCalculation.py
RiboMiner/ProcessPausingScore.py
RiboMiner/RPFdist.py
RiboMiner/ReadsLengthOfSpecificRegions.py
RiboMiner/RiboDensityAroundTripleteAAMotifs.py
RiboMiner/RiboDensityAtEachKindAAOrCodon.py
RiboMiner/RiboDensityAtEachPosition.py
RiboMiner/RiboDensityForSpecificRegion.py
RiboMiner/RiboDensityOfDiffFrames.py
RiboMiner/StatisticReadsOnDNAsContam.py
RiboMiner/__init__.py
RiboMiner/cAI.py
RiboMiner/cAIPlot.py
RiboMiner/enrichmentMeanDensity.py
RiboMiner/hydropathyCharge.py
RiboMiner/tAI.py
RiboMiner/tAIPlot.py
RiboMiner-0.2.3.2.1.dist-info/LICENSE
RiboMiner-0.2.3.2.1.dist-info/METADATA
RiboMiner-0.2.3.2.1.dist-info/WHEEL
RiboMiner-0.2.3.2.1.dist-info/entry_points.txt
RiboMiner-0.2.3.2.1.dist-info/top_level.txt
RiboMiner-0.2.3.2.1.dist-info/RECORD
