Metadata-Version: 2.1
Name: RiboMiner
Version: 0.2.3.2.1
Summary: A python toolset for mining multi-dimensional features of the translatome with ribosome profiling data
Home-page: https://github.com/xryanglab/RiboMiner
Author: Li Fajin
Author-email: sherkinglee@gmail.com
License: GPLv3.0
Keywords: Analysis for ribosome profiling data.
Platform: UNKNOWN
Classifier: Development Status :: 4 - Beta
Classifier: Intended Audience :: Science/Research
Classifier: Topic :: Scientific/Engineering :: Bio-Informatics
Classifier: Environment :: Console
Classifier: Programming Language :: Python :: 3
Classifier: Operating System :: Unix
Requires-Python: >=3.6
Requires-Dist: matplotlib (>=2.1.0)
Requires-Dist: numpy (>=1.16.4)
Requires-Dist: pandas (>=0.24.2)
Requires-Dist: pysam (>=0.15.2)
Requires-Dist: scipy (>=1.1.0)
Requires-Dist: seaborn (>=0.8.1)
Requires-Dist: biopython (>=1.70)
Requires-Dist: HTSeq
Requires-Dist: RiboCode (>=1.2.10)
Requires-Dist: pysamstats
